CONTRIBUTORS.txt
LICENSE.txt
MANIFEST.in
README
everything-requirements.txt
minimum-requirements.txt
pip-log.txt
setup.py
demos/__init__.py
demos/chat/__init__.py
demos/chat/run.py
demos/chat/settings.py
demos/spritzer/__init__.py
demos/spritzer/run.py
demos/spritzer/settings.py
demos/spritzer/spritzer_handler.py
hurricane/__init__.py
hurricane/base.py
hurricane/runner.py
hurricane/utils.py
hurricane.egg-info/PKG-INFO
hurricane.egg-info/SOURCES.txt
hurricane.egg-info/dependency_links.txt
hurricane.egg-info/not-zip-safe
hurricane.egg-info/top_level.txt
hurricane/handlers/__init__.py
hurricane/handlers/base.py
hurricane/handlers/comet.py
hurricane/handlers/logging.py
hurricane/handlers/printing.py
hurricane/handlers/random_data.py
hurricane/handlers/twitter.py
hurricane/managers/__init__.py
hurricane/managers/base.py
hurricane/managers/ipc.py
hurricane/managers/stompqueue.py
hurricane/media/js/comet.js
hurricane/media/js/jquery-1.3.2.min.js
hurricane/media/js/json2.js