Metadata-Version: 1.0
Name: hurricane
Version: 0.1
Summary: Hurricane is a project for easily creating Comet web applications
Home-page: http://github.com/ericflo/hurricane
Author: The Hurricane Development Team
Author-email: floguy+hurricane@gmail.com
License: BSD
Keywords: comet,asynchronous,messages,messaging,framework
Platform: UNKNOWN
Classifier: Programming Language :: Python
Classifier: Topic :: Software Development :: Libraries :: Python Modules
Classifier: Topic :: Software Development :: Libraries :: Application Frameworks
Classifier: Environment :: Web Environment
